ddmq/__init__.py
ddmq/broker.py
ddmq/cli.py
ddmq/message.py
ddmq-0.9.14.dist-info/LICENSE
ddmq-0.9.14.dist-info/METADATA
ddmq-0.9.14.dist-info/WHEEL
ddmq-0.9.14.dist-info/entry_points.txt
ddmq-0.9.14.dist-info/top_level.txt
ddmq-0.9.14.dist-info/RECORD
