Metadata-Version: 2.1
Name: ddmq
Version: 0.9.14
Summary: A file based serverless messaging queue
Home-page: https://github.com/ddmq/ddmq
Author: Martin Dahlö
Author-email: m.dahlo@gmail.com
License: UNKNOWN
Platform: UNKNOWN
Classifier: Programming Language :: Python :: 3
Classifier: Programming Language :: Python :: 2.7
Classifier: License :: OSI Approved :: MIT License
Classifier: Operating System :: OS Independent
Requires-Dist: pyyaml
